candlestick/__init__.py
candlestick/candlestick.py
candlestick/setup.py
candlestick/patterns/__init__.py
candlestick/patterns/bearish_engulfing.py
candlestick/patterns/bullish_engulfing.py
candlestick/patterns/candlestick_finder.py
candlestick/patterns/dark_cloud_cover.py
candlestick/patterns/evening_star.py
candlestick/patterns/evening_star_doji.py
candlestick/patterns/hammer.py
candlestick/patterns/morning_star.py
candlestick/patterns/piercing_pattern.py
candlestick/patterns/shooting_star.py
nikhil_candlesticks-0.0.1.dist-info/LICENSE
nikhil_candlesticks-0.0.1.dist-info/METADATA
nikhil_candlesticks-0.0.1.dist-info/WHEEL
nikhil_candlesticks-0.0.1.dist-info/top_level.txt
nikhil_candlesticks-0.0.1.dist-info/RECORD
