Metadata-Version: 2.1
Name: nikhil-candlesticks
Version: 0.0.1
Summary: candlestick patterns
Author: Nikhil
Author-email: cnikhil247@gmail.com
Keywords: candlesticks,patterns,reversals,nikhil,trading
Classifier: Development Status :: 1 - Planning
Classifier: Intended Audience :: Developers
Classifier: Programming Language :: Python :: 3
Classifier: Operating System :: Unix
Classifier: Operating System :: MacOS :: MacOS X
Classifier: Operating System :: Microsoft :: Windows
License-File: LICENSE
